Spectra/K_est.py
Spectra/Spectra.py
Spectra/Spectra_attn.py
Spectra/Spectra_gpu.py
Spectra/Spectra_util.py
Spectra/__init__.py
Spectra/attend.py
Spectra/data/default_gene_sets.json
Spectra/data/sample_data.h5ad
Spectra/initialization.py
Spectra/load/__init__.py
Spectra/load/default_gene_sets.py
Spectra/load/sample_data.py
scspectra-0.2.1.dist-info/LICENSE.md
scspectra-0.2.1.dist-info/METADATA
scspectra-0.2.1.dist-info/WHEEL
scspectra-0.2.1.dist-info/RECORD
